{
  "id": 10,
  "date": "2025-05-04",
  "title": "it is an ill wind (that blows nobody any good)",
  "data": {
    "音标": "",
    "释义": "An idiom said to show that even a very bad situation must have some good results",
    "例句": "\"What a day! I left my keys in my apartment, slipped on stairs, and my boss has been so mean to me the whole day!\"\n\"Oh no. But I believe the saying, it is an ill wind, there must have been SOMETHING good, right?\"\n\"Yeah, I won a lottery!\"",
    "备注": "Try to link this back to Chinese four-character idioms.",
    "source": ""
  },
  "status": "未审阅"
}